{
    "id": 1147141,
    "title": {
        "en": "Annual Meeting 2017",
        "cy": "Cyfarfod Blynyddol  a G\u0175yl Haf 2017"
    },
    "nodeType": "item",
    "url": "http:\/\/drupalvm.local\/items\/1147141",
    "created": 1562065061,
    "updated": 1562065061,
    "status": "published",
    "type": "item",
    "description": {
        "en": "Competition \u2013 Sampler\/Cross Stitch: 2nd Sarah East, Treforus branch, West Glamorgan.",
        "cy": "Cystadleuaeth Sampleri\/Croesbwyth: 2il Sarah East, Cangen Treforus, Rhanbarth Gorllewin Morgannwg."
    },
    "author": {
        "id": 7859,
        "name": "Merched y Wawr"
    },
    "creator": "Delyth Fletcher",
    "owner": "Delyth Fletcher",
    "publisher": "",
    "copyright": [
        {
            "holder": [],
            "year": null,
            "type": ""
        },
        {
            "holder": [],
            "year": null,
            "type": ""
        }
    ],
    "license": {
        "reproducedPermission": [],
        "additionalText": [],
        "type": null
    },
    "tags": [
        "annual meeting",
        "cyfarfod blynyddol",
        "g\u0175yl haf",
        "2017"
    ],
    "when": [],
    "what": [],
    "learn": [],
    "locations": [],
    "files": [
        {
            "originalFilename": "df_myw_884.jpg",
            "url": "http:\/\/drupalvm.local\/sites\/default\/files\/images\/2019\/July\/df_myw_884.jpg",
            "type": "image",
            "target_id": "1147136"
        }
    ],
    "original_item_url": {
        "en": "",
        "cy": ""
    },
    "guid": "",
    "publisher_ref": ""
}