{
    "id": 754286,
    "title": {
        "en": "A collection of photographs of Merched y Wawr Trawsfynydd, Meirionnydd",
        "cy": "Casgliad o luniau o gangen Merched y Wawr Trawsfynydd, Meirionnydd."
    },
    "nodeType": "item",
    "url": "http:\/\/drupalvm.local\/items\/754286",
    "created": 1516958700,
    "updated": 1516958700,
    "status": "published",
    "type": "item",
    "description": {
        "en": "Llyfryn \u2018Teithiau Cangen Trawsfynydd\u2019 cyhoeddwyd yn 2012.",
        "cy": "Llyfryn \u2018Teithiau Cangen Trawsfynydd\u2019 cyhoeddwyd yn 2012."
    },
    "author": {
        "id": 7859,
        "name": "Merched y Wawr"
    },
    "creator": "Cangen Trawsfynydd",
    "owner": "Cangen Trawsfynydd",
    "publisher": "",
    "copyright": [
        {
            "holder": [],
            "year": null,
            "type": ""
        },
        {
            "holder": [],
            "year": null,
            "type": ""
        }
    ],
    "license": {
        "reproducedPermission": [],
        "additionalText": [],
        "type": null
    },
    "tags": [
        "merched y wawr",
        "Womens History",
        "Clubs and Organisations",
        "Trawsfynydd",
        "Meirionnydd",
        "MYW",
        "Dathlu 50",
        "Hanes Merched",
        "Cymdeithasau a Chlybiau",
        "Cangen Trawsfynydd",
        "Llyfrau Merched y Wawr",
        "Teithiau Merched y Wawr"
    ],
    "when": [
        "2010s"
    ],
    "what": [
        "Societies and clubs"
    ],
    "learn": [],
    "locations": [
        {
            "lat": "52.902317000000",
            "lon": "-3.923549000000",
            "description": {
                "en": "Trawsfynydd",
                "cy": "Trawsfynydd"
            }
        }
    ],
    "files": [
        {
            "originalFilename": "MYW_GOG_MEIRIONNYDD_TRAWSFYNYDD_011.jpg",
            "url": "http:\/\/drupalvm.local\/sites\/default\/files\/images\/2018\/January\/MYW_GOG_MEIRIONNYDD_TRAWSFYNYDD_011.jpg",
            "type": "image",
            "target_id": "754241"
        },
        {
            "originalFilename": "MYW_GOG_MEIRIONNYDD_TRAWSFYNYDD_012.jpg",
            "url": "http:\/\/drupalvm.local\/sites\/default\/files\/images\/2018\/January\/MYW_GOG_MEIRIONNYDD_TRAWSFYNYDD_012.jpg",
            "type": "image",
            "target_id": "754246"
        },
        {
            "originalFilename": "MYW_GOG_MEIRIONNYDD_TRAWSFYNYDD_013.jpg",
            "url": "http:\/\/drupalvm.local\/sites\/default\/files\/images\/2018\/January\/MYW_GOG_MEIRIONNYDD_TRAWSFYNYDD_013.jpg",
            "type": "image",
            "target_id": "754251"
        },
        {
            "originalFilename": "MYW_GOG_MEIRIONNYDD_TRAWSFYNYDD_014.jpg",
            "url": "http:\/\/drupalvm.local\/sites\/default\/files\/images\/2018\/January\/MYW_GOG_MEIRIONNYDD_TRAWSFYNYDD_014.jpg",
            "type": "image",
            "target_id": "754256"
        },
        {
            "originalFilename": "MYW_GOG_MEIRIONNYDD_TRAWSFYNYDD_015.jpg",
            "url": "http:\/\/drupalvm.local\/sites\/default\/files\/images\/2018\/January\/MYW_GOG_MEIRIONNYDD_TRAWSFYNYDD_015.jpg",
            "type": "image",
            "target_id": "754261"
        },
        {
            "originalFilename": "MYW_GOG_MEIRIONNYDD_TRAWSFYNYDD_016.jpg",
            "url": "http:\/\/drupalvm.local\/sites\/default\/files\/images\/2018\/January\/MYW_GOG_MEIRIONNYDD_TRAWSFYNYDD_016.jpg",
            "type": "image",
            "target_id": "754266"
        },
        {
            "originalFilename": "MYW_GOG_MEIRIONNYDD_TRAWSFYNYDD_017.jpg",
            "url": "http:\/\/drupalvm.local\/sites\/default\/files\/images\/2018\/January\/MYW_GOG_MEIRIONNYDD_TRAWSFYNYDD_017.jpg",
            "type": "image",
            "target_id": "754271"
        },
        {
            "originalFilename": "MYW_GOG_MEIRIONNYDD_TRAWSFYNYDD_010.jpg",
            "url": "http:\/\/drupalvm.local\/sites\/default\/files\/images\/2018\/January\/MYW_GOG_MEIRIONNYDD_TRAWSFYNYDD_010.jpg",
            "type": "image",
            "target_id": "754276"
        }
    ],
    "original_item_url": {
        "en": "",
        "cy": ""
    },
    "guid": "",
    "publisher_ref": ""
}